notebook_to_pdf/__init__.py
notebook_to_pdf/converter.py
tests/__init__.py
tests/test_converter.py
JupyterToPDF-0.0.1.dist-info/METADATA
JupyterToPDF-0.0.1.dist-info/WHEEL
JupyterToPDF-0.0.1.dist-info/entry_points.txt
JupyterToPDF-0.0.1.dist-info/top_level.txt
JupyterToPDF-0.0.1.dist-info/RECORD
