Metadata-Version: 2.1
Name: JupyterToPDF
Version: 0.0.1
Summary: A simple tool to convert Jupyter notebooks to PDF
Home-page: https://github.com/nomannayeem
Author: Nayeem Islam
Author-email: nayeem60151126@gmail.com
Classifier: Development Status :: 3 - Alpha
Classifier: Intended Audience :: Developers
Classifier: License :: OSI Approved :: MIT License
Classifier: Programming Language :: Python :: 3
Classifier: Programming Language :: Python :: 3.8
Requires-Python: >=3.6
Requires-Dist: pdfkit
